vnpy_okex_pro/__init__.py
vnpy_okex_pro/okex_gateway.py
vnpy_okex_pro-2023.4.14.4.dist-info/LICENSE
vnpy_okex_pro-2023.4.14.4.dist-info/METADATA
vnpy_okex_pro-2023.4.14.4.dist-info/WHEEL
vnpy_okex_pro-2023.4.14.4.dist-info/top_level.txt
vnpy_okex_pro-2023.4.14.4.dist-info/RECORD
